MANIFEST.in
README.rst
blackjack.py
setup.py
version.txt
blackjack.egg-info/PKG-INFO
blackjack.egg-info/SOURCES.txt
blackjack.egg-info/dependency_links.txt
blackjack.egg-info/top_level.txt