Metadata-Version: 1.0
Name: blackjack
Version: 1.1.1
Summary: Red-black trees
Home-page: http://github.com/MostAwesomeDude/blackjack
Author: Corbin Simpson
Author-email: cds@corbinsimpson.com
License: MIT/X11
Platform: UNKNOWN
